process_spectra/__init__.py
process_spectra/funcs/__init__.py
process_spectra/funcs/piezo_fbg.py
process_spectra/utils/__init__.py
process_spectra/utils/fbg.py
process_spectra-0.2.9.dist-info/LICENSE
process_spectra-0.2.9.dist-info/METADATA
process_spectra-0.2.9.dist-info/WHEEL
process_spectra-0.2.9.dist-info/RECORD
